chronon/__init__.py
chronon/core/__init__.py
chronon/core/event.py
chronon/core/manager.py
chronon/core/process.py
chronon/core/resource.py
chronon/core/user.py
chronon/helpers/time.py
chronon/managers/__init__.py
chronon/managers/event_manager.py
chronon/managers/process_manager.py
chronon/managers/resource_manager.py
chronon/managers/user_manager.py
chronon-0.0.2.dist-info/LICENSE
chronon-0.0.2.dist-info/WHEEL
chronon-0.0.2.dist-info/METADATA
chronon-0.0.2.dist-info/RECORD
