Metadata-Version: 2.1
Name: chronon
Version: 0.0.2
Summary: Discrete event simulator
Author: Ricardo Amigo
Author-email: ricardo.amigo@mclaren.com
Requires-Python: >=3.7,<4.0
Classifier: Programming Language :: Python :: 3
Classifier: Programming Language :: Python :: 3.7
Classifier: Programming Language :: Python :: 3.8
Requires-Dist: pandas (>=1.1.3,<2.0.0)
Requires-Dist: simpy (>=4.0.1,<5.0.0)
